pyshop/__init__.py
pyshop/shop_runner.py
pyshop/helpers/__init__.py
pyshop/helpers/commands.py
pyshop/helpers/environment_helper.py
pyshop/helpers/time.py
pyshop/helpers/timeseries.py
pyshop/helpers/typing_annotations.py
pyshop/lp_model/__init__.py
pyshop/lp_model/index.py
pyshop/lp_model/lp_model.py
pyshop/lp_model/row.py
pyshop/lp_model/var.py
pyshop/shopcore/__init__.py
pyshop/shopcore/command_builder.py
pyshop/shopcore/model_builder.py
pyshop/shopcore/pq_curve_generation.py
pyshop/shopcore/script_generator.py
pyshop/shopcore/shop_api.py
pyshop/shopcore/shop_rest.py
sintef_pyshop-1.5.1.dist-info/licenses/LICENSE
sintef_pyshop-1.5.1.dist-info/METADATA
sintef_pyshop-1.5.1.dist-info/WHEEL
sintef_pyshop-1.5.1.dist-info/top_level.txt
sintef_pyshop-1.5.1.dist-info/RECORD
