Metadata-Version: 2.4
Name: sintef-pyshop
Version: 1.5.1
Summary: Python interface to SHOP
Home-page: http://www.sintef.no/programvare/SHOP
Author: SINTEF Energy Research
Author-email: support.energy@sintef.no
License: MIT
Project-URL: Documentation, https://shop.sintef.energy/documentation/tutorials/pyshop/
Project-URL: Source, https://gitlab.sintef.no/energy/shop/pyshop
Project-URL: Tracker, https://shop.sintef.energy/tickets
Classifier: Development Status :: 5 - Production/Stable
Classifier: License :: OSI Approved :: MIT License
Classifier: Intended Audience :: Developers
Classifier: Intended Audience :: End Users/Desktop
Classifier: Intended Audience :: Education
Classifier: Intended Audience :: Science/Research
Classifier: Topic :: Scientific/Engineering
Classifier: Programming Language :: Python :: 3.9
Classifier: Programming Language :: Python :: 3.10
Classifier: Programming Language :: Python :: 3.11
Classifier: Programming Language :: Python :: 3.12
Classifier: Programming Language :: Python :: 3.13
Requires-Python: >=3.9
License-File: LICENSE
Requires-Dist: pandas
Requires-Dist: numpy
Requires-Dist: graphviz
Requires-Dist: plotly
Requires-Dist: packaging
Requires-Dist: requests
Dynamic: author
Dynamic: author-email
Dynamic: classifier
Dynamic: description
Dynamic: description-content-type
Dynamic: home-page
Dynamic: license
Dynamic: license-file
Dynamic: project-url
Dynamic: requires-dist
Dynamic: requires-python
Dynamic: summary
